{
  "sourceData": {
    "path": "X:\\RRD018-2025_OU_(PILS)",
    "folderName": "RRD018-2025_OU_(PILS)",
    "fileCount": 1763,
    "totalSize": 352921712,
    "totalSizeFormatted": "336.6 MB"
  },
  "destinationPath": "X:\\RRD018-2025_OU_(PILS)\\",
  "projectInfo": {
    "archiveId": "RRD018-2025",
    "location": "OU",
    "documentType": "PILS",
    "pdfPath": "X:\\RRD018-2025_OU_(PILS)\\PDFs_RRD018-2025",
    "comlistPath": "X:\\RRD018-2025_OU_(PILS)\\RRD018-2025_PILS_COM_List.xlsx",
    "isValid": true
  },
  "projectId": "12",
  "uiState": {
    "autoParseEnabled": true,
    "autoSelectPathEnabled": true,
    "autoFindPdfEnabled": true,
    "autoFindComlistEnabled": true,
    "createSubfolderEnabled": true
  },
  "isValidated": 12
}